{"post_id":"futaland-054","text":"SẴN SÀNG BÙNG NỔ CÙNG SỰ KIỆN VINH DANH ĐẠI LÝ VÀ KÍCH HOẠT CHIẾN DỊCH THÁP A, FUTA RESIDENCE - ĐÀ NẴNG TIMES SQUARE \nChỉ còn ít giờ nữa, sự kiện vinh danh đại lý và kích hoạt chiến dịch Tháp A dự án FUTA Residence sẽ chính thức diễn ra, đánh dấu một cột mốc quan trọng cho hành trình tăng tốc cuối năm của toàn hệ thống đại lý.\nKhông đơn thuần là một buổi đào tạo sản phẩm, sự kiện hôm nay là nơi:\n- Hội tụ các đại lý chiến lược đồng hành từ giai đoạn đầu.\n- Kích hoạt tinh thần ra quân – bứt tốc – chinh phục mục tiêu tháng 12.\n- Và chính thức mở màn cho giai đoạn tăng tốc cao điểm của Tháp A.\nĐiểm nhấn được mong chờ nhất chính là nội dung đào tạo chuyên sâu Tháp A. Những thông tin chiến lược, lợi thế cạnh tranh, tư duy bán hàng thực chiến và định hướng chốt giao dịch trong giai đoạn nước rút sẽ được “giải mã” rõ ràng ngay tại sự kiện.\nBên cạnh đó, chương trình còn có:\n- Phần vinh danh 09 đại lý chiến lược giai đoạn đầu.\n- Trao chứng nhận 04 đại lý chiến lược phân phối mới.\n- Công bố các chính sách động lực mới cho chiến dịch Tháp A.\n- Và đặc biệt là phần Q&A 10 câu hỏi có thưởng, hứa hẹn khuấy động không khí và đẩy năng lượng của đội ngũ sales lên mức cao nhất.\nKhông khí đã sẵn sàng. Đội hình đã vào vị trí. Chỉ còn chờ giờ G để bùng nổ tốc độ và kết quả!\n Hẹn gặp các chiến binh tại sự kiện chiều nay – nơi Tháp A chính thức vào guồng, và cuộc đua cuối năm thật sự bắt đầu!\n#FUTALand #CountdownGioG #DaoTaoThapA #ChienDichCuoiNam #BatTocThang12 #SalesRaQuan #VinhDanhDaiLy #BatDongSan","style":"facebook_post","sub_type":"sales_opening","title":"SẴN SÀNG BÙNG NỔ CÙNG SỰ KIỆN VINH DANH ĐẠI LÝ VÀ KÍCH HOẠT CHIẾN DỊCH THÁP A, FUTA RESIDENCE - ĐÀ NẴNG TIMES SQUARE","source":""}